Final Submission/doorlock/doorlock.v
// DOOR LOCK

// Group 34

// Prashant Mittal 2020CSB1113
// Anubhav Kataria 2020CSB1073

// Main module of Password Door Lock System

module door_lock(reset, password, newpass, confpass, command, cout);
  
  // original is an implementation of 4x4 RAM which stores the correct password of the door
  // The initial password of the door is 1234
  reg [0:3][0:3] original = {4'h1,4'h2,4'h3,4'h4};
  
  // reset is a 1 bit input which tells whether doorlock is in reset mode or not
  // 1 means doorlock is in reset mode
  input reset;
  
  // password is a 4x4 RAM which stores the input password given by the user
  input [0:3][0:3] password;
  
  // newpass is a 4x4 RAM which stores the password to be updated entered by the user
  input [0:3][0:3] newpass;
  
  // confpass is a 4x4 RAM which stores the password as confirm of the newpass entered by the user
  input [0:3][0:3] confpass;
  
  // command is a 1 bit input which tells whether we want to unlock the door or update the password
  // If command is 1 that means door has to be unlocked and if it is 0 password has to be updated
  input command;
  
  // cout is a 1 bit output that tells whether the door is in unlocked state or the locked state
  // If cout is 1 that means door is unlocked else locked
  output reg cout = 0;
  
  // All the password checking, reseting and updating is done inside the always block
  always @(*)
    
    begin
      
      // Making cout 0 because initially the door is locked
      cout = 0;
      
      if(reset)
        
        begin
          
          // If reset is is 1 then the password changes to the original password entered by the user
          original = password;
          $display("Reset Mode");
          
          // Here the door lock went in reset mode and password was changed
          
        end
      
      else 
        
        begin
          
          // If reset is zero we check whether the entered password is correct or not
          if(password == original)  
            
            begin
              
			  // If the password is correct we check what is the command given by the user
              if(command) 
                
                begin
                  
				  // If command is 1 then the door has been unlocked
                  // it is displayed that the door has been unlocked
                  $display("Door Unlocked");
                  
                  // Making cout 1 because the door has been unlocked
                  cout = 1;
                  
                  // Here the door has been unlocked
                  
                end
              
              else
                
                begin
                  
                  // Else if command is 0 then it means the user wants to reset the password
                  if(newpass == confpass) 
                    
                    begin
                      
                      // If confpass is same as newpass then then it can update the original password
                      // Changing the original password to newpass
                      original = newpass; 
                      
                      // Printing that the doorlock has been updated
					  $display("Password Updated");
                      
                      // Here the password has been updated to the new one 
                      
                    end
                                   
                  else 
                    
                    begin
                      
                      // If new password and confirmatory password does not match an error is thrown
                      $display("Error! Password Didn't Match"); // ERROR
                      
                      // Here it tells that new password and confirmatory password doesn't match
                      
                    end
                  
                end
              
            end
          
          else 
            
            begin
              
              // If user has enter wrong password an error is thrown
              $display("Wrong Password"); // ERROR
              
              // Here the password entered was incorrect and hence ERROR was displayed
              
            end 
          
        end
      
    end
  
endmodule

Final Submission/testbench/testbench.v
module doorlock();

  reg r;
  
  reg [0:3][0:3] p;
  
  reg [0:3][0:3] p1;
  
  reg [0:3][0:3] p2;
  
  reg c;
  
  wire cout;
  
  // r is to reset the password
  // p is the entered password
  // p1 stores new password to be changed
  // p2 stores confirmed new password
  // c is command to change or unlock the door
  // cout tells whether door is locked or unlocked
  
  door_lock d1(
    .reset(r), 
    .password(p),
    .newpass(p1),
    .confpass(p2),
    .command(c), 
    .cout(cout)
  );

	initial
      begin
        
		r = 0;
        p = {4'h1, 4'h2, 4'h3, 4'h4};
		c = 1;
		#100;

		r = 1;
        p = {4'h2, 4'h2, 4'h0, 4'h7};
        c = 1;
		#100;

		r = 0;
        p = {4'h2, 4'h2, 4'h0, 4'h7};
		c = 1;
		#100;

		r = 0;
		p = {4'h6, 4'h7, 4'h0, 4'h7};
		c = 1;
		#100;

		r = 0;
        p = {4'h2, 4'h2, 4'h0, 4'h7};
		c = 0;
        p1 = {4'h9, 4'h3, 4'h6, 4'h5};
        p2 = {4'h4, 4'h9, 4'h1, 4'h3};
		#100;

		r = 0;
        p = {4'h2, 4'h2, 4'h0, 4'h7};
		c = 0;
        p1 = {4'h4, 4'h9, 4'h1, 4'h3};
        p2 = {4'h4, 4'h9, 4'h1, 4'h3};
		#100;

		r = 0;
		p = {4'h4, 4'h9, 4'h1, 4'h3};
		c = 1;
		#100;

		r = 1;
		p = {4'h4, 4'h9, 4'h1, 4'h3};
        c = 1;
		#100;

		r = 1;
		p = {4'h6, 4'h1, 4'h2, 4'h6};
        c = 1;
		#100;

		r = 0;
		p = {4'h6, 4'h1, 4'h2, 4'h6};
		c = 1;
		#100;

		r = 0;
		p = {4'h9, 4'h6, 4'h4, 4'h6};
		c = 0;
        p1 = {4'h9, 4'h6, 4'h4, 4'h6};
        p2 = {4'h9, 4'h6, 4'h4, 4'h6};
		#100;

		r = 0;
        p = {4'h9, 4'h6, 4'h4, 4'h5};
		c = 1;
		#100;

		r = 0;
		p = {4'h6, 4'h1, 4'h2, 4'h6};
		c = 1;
		#100;

		r = 0;
		p = {4'h9, 4'h2, 4'h4, 4'h5};
		c = 1;
		#100;

		r = 1;
		p = {4'h2, 4'h4, 4'h1, 4'h6};
        c = 1;
		#100;

		r = 0;
        p = {4'h1, 4'h4, 4'h1, 4'h6};
		c = 1;
		#100;

		r = 0;
        p = {4'h2, 4'h4, 4'h1, 4'h6};
		c = 0;
        p1 = {4'h1, 4'h9, 4'h6, 4'h7};
        p2 = {4'h1, 4'h9, 4'h6, 4'h7};
		#100;

		r = 0;
		p = {4'h1, 4'h9, 4'h6, 4'h7};
		c = 1;
		#100;


        
	end
      
  initial
    begin
      $dumpfile("doorlock.vcd");
      $dumpvars;
      
    end
endmodule

Final Submission/output/doorlock.vcd
$date
	Sun Nov 21 12:55:20 2021
$end
$version
	Icarus Verilog
$end
$timescale
	1s
$end
$scope module doorlock $end
$var wire 1 ! cout $end
$var reg 1 " c $end
$var reg 16 # p [15:0] $end
$var reg 16 $ p1 [15:0] $end
$var reg 16 % p2 [15:0] $end
$var reg 1 & r $end
$scope module d1 $end
$var wire 1 " command $end
$var wire 16 ' confpass [15:0] $end
$var wire 16 ( newpass [15:0] $end
$var wire 16 ) password [15:0] $end
$var wire 1 & reset $end
$var reg 1 ! cout $end
$var reg 16 * original [15:0] $end
$upscope $end
$upscope $end
$enddefinitions $end
#0
$dumpvars
b1001000110100 *
b1001000110100 )
bx (
bx '
0&
bx %
bx $
b1001000110100 #
1"
1!
$end
#100
b10001000000111 *
0!
b10001000000111 #
b10001000000111 )
1&
#200
1!
0&
#300
0!
b110011100000111 #
b110011100000111 )
#400
b100100100010011 %
b100100100010011 '
b1001001101100101 $
b1001001101100101 (
0"
b10001000000111 #
b10001000000111 )
#500
b100100100010011 *
b100100100010011 $
b100100100010011 (
#600
1!
1"
b100100100010011 #
b100100100010011 )
#700
0!
1&
#800
b110000100100110 *
b110000100100110 #
b110000100100110 )
#900
1!
0&
#1000
0!
b1001011001000110 %
b1001011001000110 '
b1001011001000110 $
b1001011001000110 (
0"
b1001011001000110 #
b1001011001000110 )
#1100
1"
b1001011001000101 #
b1001011001000101 )
#1200
1!
b110000100100110 #
b110000100100110 )
#1300
0!
b1001001001000101 #
b1001001001000101 )
#1400
b10010000010110 *
b10010000010110 #
b10010000010110 )
1&
#1500
b1010000010110 #
b1010000010110 )
0&
#1600
b1100101100111 *
b1100101100111 %
b1100101100111 '
b1100101100111 $
b1100101100111 (
0"
b10010000010110 #
b10010000010110 )
#1700
1!
1"
b1100101100111 #
b1100101100111 )
